Metadata-Version: 2.1
Name: jk-asyncio-syncasync
Version: 0.2019.10.19
Summary: This python module enables asyncio based functions/methods to invoke classic synchroneous functions/methods. This is implemented by delegating execution of to a thread pool.
Home-page: https://github.com/jkpubsrc/ython-module-jk-asyncio-syncasync
Author: Jürgen Knauth
Author-email: pubsrc@binary-overflow.de
License: Apache 2.0
Download-URL: https://github.com/jkpubsrc/ython-module-jk-asyncio-syncasync/tarball/0.2019.10.19
Keywords: asyncio
Platform: UNKNOWN
Classifier: Development Status :: 5 - Production/Stable
Classifier: License :: OSI Approved :: Apache Software License
